set_github_secret/__init__.py
set_github_secret/set_github_secret.py
set_github_secret/utils/__init__.py
set_github_secret/utils/frozen_dir.py
set_github_secret-0.1.0.dist-info/LICENSE
set_github_secret-0.1.0.dist-info/METADATA
set_github_secret-0.1.0.dist-info/WHEEL
set_github_secret-0.1.0.dist-info/entry_points.txt
set_github_secret-0.1.0.dist-info/RECORD
