Metadata-Version: 2.1
Name: set-github-secret
Version: 0.1.0
Summary: set github secret
License: Apache-2.0
Author: liuyuqi-dellpc
Author-email: liuyuqi.gov@msn.cn
Requires-Python: >=3.11,<4.0
Classifier: License :: OSI Approved :: Apache Software License
Classifier: Programming Language :: Python :: 3
Classifier: Programming Language :: Python :: 3.11
Classifier: Programming Language :: Python :: 3.12
Requires-Dist: requests (>=2.22.0,<3.0.0)
